sdto/__init__.py
sdto/__main__.py
sdto/sdto.py
sdto-0.1.7.dist-info/LICENSE
sdto-0.1.7.dist-info/WHEEL
sdto-0.1.7.dist-info/METADATA
sdto-0.1.7.dist-info/RECORD
