Metadata-Version: 2.1
Name: sdto
Version: 0.1.7
Summary: Subdomain takeover finder
Home-page: https://github.com/scanfactory/sdto
License: MIT
Keywords: subdomain-takeover,scanner,cybersecurity,security,takeover
Author: godpleaseno
Author-email: zfrty@protonmail.com
Requires-Python: >=3.8,<4.0
Classifier: License :: OSI Approved :: MIT License
Classifier: Programming Language :: Python :: 3
Classifier: Programming Language :: Python :: 3.8
Classifier: Programming Language :: Python :: 3.9
Classifier: Programming Language :: Python :: 3.10
Classifier: Programming Language :: Python :: 3.11
Classifier: Programming Language :: Python :: 3.10
Classifier: Programming Language :: Python :: 3.8
Classifier: Programming Language :: Python :: 3.9
Classifier: Topic :: Security
Requires-Dist: aiohttp (>=3.8.3,<4.0.0)
Project-URL: Repository, https://github.com/scanfactory/sdto
